syftbox_enclave/__init__.py
syftbox_enclave/client.py
syftbox_enclave/orchestra.py
syftbox_enclave/py.typed
syftbox_enclave/utils.py
syftbox_enclave-0.1.4.dist-info/METADATA
syftbox_enclave-0.1.4.dist-info/WHEEL
syftbox_enclave-0.1.4.dist-info/licenses/LICENSE
syftbox_enclave-0.1.4.dist-info/RECORD
