Metadata-Version: 2.4
Name: syftbox-enclave
Version: 0.1.4
Summary: SyftBox Enclave provides an interface for Enclave Deployments in SyftBox.
License-File: LICENSE
Requires-Python: >=3.12
Requires-Dist: ipywidgets>=8.1.7
Requires-Dist: loguru>=0.7.3
Requires-Dist: matplotlib>=3.10.3
Requires-Dist: pandas>=2.2.3
Requires-Dist: pydantic>=2.11.5
Requires-Dist: rich>=14.0.0
Requires-Dist: syft-core>=0.2.3
